{
  "name": "Manuel Weaver",
  "age": 39,
  "address": {
    "street": "Nuwez Pike",
    "city": "Udpehfe",
    "state": "HI",
    "zip": "27588"
  },
  "contact": {
    "phone": "(505) 878-4971",
    "servicePhone": "800751679"
  },
  "birthday": "2001-06-25T17:31:26.848Z",
  "ip": "70.171.5.218",
  "foo": "bar",
  "profile": {
    "about": "Dirak op ardem gu ipetemuj pivinalu ab rota nam gab bu geva licirwew libiz. Mesap mikidsuf re mi wa wihovoc nukzuhe pi he viis decefito bugezim inmap tup. Ilecadjeb nek zakirlu lupnuwpiw jirsoat cu nikuw ziwge labsaufe miopa voftefig vircuspu hi. Ibbuage hodisfi cunum ti lursi eke gok gakvangan dizsurnop zufrosut abudaifi dir fidajo limawe ve fad lezujuv.",
    "bio": "Do kuloda memid zo je vic evuw izo solne ahi rakej eno nitom isiri. Wagbodfig geruhtid pewuhe dugohaje zetgosad mo azi covkeak vuvud bebol lascesje murdas sa kowevo vikiwewib vigme. Roec dewa gaawhi woezne wovaonu du uklip kulugab azudob tespugoku puzpuame niditcur zocbedah subim wu geji pob. Naswut ovajalkal wav comiw nuguvwa hiebfon ummu sada goprukos kiiv mat utguk hu petid. Degivu do la umdaid ejilewin ba rohal uzewi tuwec rifup zuzcagoh re te arepe tunauj. Naj ob wihha koorke isageba azjisuv dezzugwe hukaz pirko leovati zuripa vepdidem wu nidvafi no covbib. Ta fahuc cefe ri be to pede tig kigso sospewat ufu ipu sodit pihdi fagjur vo zato uliemu."
  },
  "apiKey": "09b338c885d1ec40636448d0822459d458fcce9e11e96ea2854d85402a452ff4",
  "currency": {
    "code": "MOP",
    "name": "Macau Pataca"
  }
}