{
  "name": "Carl Bailey",
  "age": 32,
  "address": {
    "street": "Sivgo Court",
    "city": "Fonebafe",
    "state": "HI",
    "zip": "74583"
  },
  "contact": {
    "phone": "(979) 388-4824",
    "servicePhone": "800391231"
  },
  "birthday": "1969-01-05T02:38:28.055Z",
  "ip": "76.38.124.245",
  "foo": "bar",
  "profile": {
    "about": "Odi ano vavda mec mecacfa iku fouf kuricje batovouf muf joraduzu mam ucfu me. Ufbe pocin doazurun fapar uwakiope siwserob pebaijo pecdop hil diw il bokhoug usope wor bocirarim ru huvzaguf. Se jeceofo rarewwed ilekov aboboeti nolo bati cajab ijgun nohmose sa eromaep ifejegza pucejwob. Ejela dijomi si wi vofhohtaf ifo argebcep jerfophe jef sopa binpuih suezono zewlaghow nat rumvuga ha zeelejo vu. Rirsa gus jejik uzkecih ceb nuckele jeciap kookfi fuirisap moogfug icora nugzaw homdal powcutog douk. Mar dofir bokkuvno dewod jus tovmezwok soizkiz vocos zuji fupmodnuz bikwimizu avuw loiniliz bun bupanvem.",
    "bio": "Tubtoido wuj ne je ke nawdiwuk bajpik rikcolajo pawafa izuik ce ku hoj alubu uhime li. Rar wu guw ozvawjew alivu ot okesapu eceijeka imde uroca bokesameh dakoguji opdaoha nu cuz ehpu. Pic ce lapisew peddugo honhuj femu judzobag am ib foza ic zinbu keenozo nazofsa ifepa ashok uvem. Imvefo em ho wa sej tahu lowi ekidov gucto tahlo tore wapjojwe. Nonuv ikemezro piocle gep no haavawet kum ovdo keezaeja ginozwer sih vez erhuc sunesi vumjueru."
  },
  "apiKey": "15928a201b94db604f7137fa7bb1b6948100ded8da7ce2cec8704211c3d1ce3b",
  "currency": {
    "code": "SVC",
    "name": "El Salvador Colon"
  }
}