{
  "name": "Logan Jimenez",
  "age": 26,
  "address": {
    "street": "Jewde Avenue",
    "city": "Pibemo",
    "state": "KY",
    "zip": "65810"
  },
  "contact": {
    "phone": "(302) 776-5687",
    "servicePhone": "800627446"
  },
  "birthday": "1966-06-26T16:16:37.024Z",
  "ip": "153.235.67.150",
  "foo": "bar",
  "profile": {
    "about": "Kiztil vi ki odobamcu kocvo neztaol zojaf ran jepebenat vujbipve luk fazag ruorhaj luckeuw vazuze finusova jimca. Gu muf redid nagsi mubtihul zioha tacrewug fo ukliv osikifgo cepdev ocfoede puhwo vikle kiararod jiwimus tehmezir. Daef edcuc milivu ic wo motop ele vilus cadu nuwo ewokaglel etovub ez rufdove. Fovadu lowu ros efo juja lalmo mimej bo hilug opzehfod zelzilcom doazu dat rejul.",
    "bio": "Iwimarav ip ecowav zo to doteccej pesuvvoj se ne redinni zizipo zafas. Fiemifol jugga jas ujven zipjinnid pi nuto onfij du momzes vo meusenu na unpal ulku. Sogpob vugef reg uw ciz mizsa rufun coztep du fi ab nejlav mor ra ev ja. Ne zaesewir cumwowo imibawe zuvcopupa uzubid cibhoj za burusi lodo evuma porufifa beno zesappil. Imofu oklapan ravcup refunodoj rim azob ovlorso cef huc ve jagovin fopunnof pe ofaega jur gubejfib ama pe. Gubwapbog efubuj ara volso usedefsum na ha ner ere jemugzi ubowevrup gek nak hapu. Voerni sano do zozmav nebowje dedufil ede tidjul mezoce vobijlu baidta soluhigo tage kovocfu hub."
  },
  "apiKey": "7c94785534a782bdd4fbcaae76a441deb757b359a7058ee2dd8a3b576cf8a5ca",
  "currency": {
    "code": "CUP",
    "name": "Cuba Peso"
  }
}